[
  {
    "Name": "TheGrandPalaceCairo",
    "Category": "Luxury",
    "Location": "Cairo, Egypt",
    "StarRating": 5
  },

  {
    "Name": "SeasideResortSharmElSheikh",
    "Category": "Resort",
    "Location": "Sharm El Sheikh, Egypt",
    "StarRating": 4
  },
  {
    "Name": "PyramidsMotelGiza",
    "Category": "Motel",
    "Location": "Giza, Egypt",
    "StarRating": 2
  },
  {
    "Name": "NileViewHotelAswan",
    "Category": "Deluxe",
    "Location": "Aswan, Egypt",
    "StarRating": 4
  },
  {
    "Name": "LuxorBoutiqueHotel",
    "Category": "Boutique",
    "Location": "Luxor, Egypt",
    "StarRating": 4
  },
  {
    "Name": "BurjAlArabDubai",
    "Category": "Luxury",
    "Location": "Dubai, UAE",
    "StarRating": 5
  },
  {
    "Name": "AtlantisThePalmDubai",
    "Category": "Resort",
    "Location": "Dubai, UAE",
    "StarRating": 5
  },
  {
    "Name": "JumeirahBeachHotelDubai",
    "Category": "Luxury",
    "Location": "Dubai, UAE",
    "StarRating": 5
  },
  {
    "Name": "TheRitzParis",
    "Category": "Luxury",
    "Location": "Paris, France",
    "StarRating": 5
  },
  {
    "Name": "LeMeuriceParis",
    "Category": "Deluxe",
    "Location": "Paris, France",
    "StarRating": 4
  },
  {
    "Name": "HotelDeCrillonParis",
    "Category": "Luxury",
    "Location": "Paris, France",
    "StarRating": 5
  },
  {
    "Name": "SofitelNice",
    "Category": "Deluxe",
    "Location": "Nice, France",
    "StarRating": 4
  },
  {
    "Name": "ThePlazaNewYork",
    "Category": "Luxury",
    "Location": "New York, USA",
    "StarRating": 5
  },
  {
    "Name": "WaldorfAstoriaNewYork",
    "Category": "Luxury",
    "Location": "New York, USA",
    "StarRating": 5
  },
  {
    "Name": "BeverlyHillsHotelLA",
    "Category": "Luxury",
    "Location": "Los Angeles, USA",
    "StarRating": 5
  },
  {
    "Name": "TheLanghamChicago",
    "Category": "Deluxe",
    "Location": "Chicago, USA",
    "StarRating": 4
  },
  {
    "Name": "HotelDanieliVenice",
    "Category": "Luxury",
    "Location": "Venice, Italy",
    "StarRating": 5
  },
  {
    "Name": "GrandHotelTremezzoLakeComo",
    "Category": "Luxury",
    "Location": "Lake Como, Italy",
    "StarRating": 5
  },
  {
    "Name": "HotelSacherFlorence",
    "Category": "Luxury",
    "Location": "Florence, Italy",
    "StarRating": 5
  },
  {
    "Name": "TheSavoyLondon",
    "Category": "Luxury",
    "Location": "London, UK",
    "StarRating": 5
  },
  {
    "Name": "Claridge",
    "Category": "Deluxe",
    "Location": "London, UK",
    "StarRating": 4
  },
  {
    "Name": "TheDorchesterLondon",
    "Category": "Luxury",
    "Location": "London, UK",
    "StarRating": 5
  },
  {
    "Name": "TheTokyoHotel",
    "Category": "Deluxe",
    "Location": "Tokyo, Japan",
    "StarRating": 4
  },
  {
    "Name": "ParkHyattTokyo",
    "Category": "Luxury",
    "Location": "Tokyo, Japan",
    "StarRating": 5
  },
  {
    "Name": "TheGinzaHotel",
    "Category": "Deluxe",
    "Location": "Ginza, Japan",
    "StarRating": 4
  },
  {
    "Name": "TheLanghamMelbourne",
    "Category": "Deluxe",
    "Location": "Melbourne, Australia",
    "StarRating": 4
  },
  {
    "Name": "CrownTowersMelbourne",
    "Category": "Luxury",
    "Location": "Melbourne, Australia",
    "StarRating": 5
  },
  {
    "Name": "SydneyHarbourHotel",
    "Category": "Deluxe",
    "Location": "Sydney, Australia",
    "StarRating": 4
  },
  {
    "Name": "FairmontBanffSprings",
    "Category": "Luxury",
    "Location": "Banff, Canada",
    "StarRating": 5
  },
  {
    "Name": "ChateauFrontenacQuebec",
    "Category": "Luxury",
    "Location": "Quebec, Canada",
    "StarRating": 5
  },
  {
    "Name": "ThePrinceHotelToronto",
    "Category": "Deluxe",
    "Location": "Toronto, Canada",
    "StarRating": 4
  },
  {
    "Name": "HotelArtsBarcelona",
    "Category": "Deluxe",
    "Location": "Barcelona, Spain",
    "StarRating": 4
  },
  {
    "Name": "PalacioDeLosDuquesMadrid",
    "Category": "Luxury",
    "Location": "Madrid, Spain",
    "StarRating": 5
  },
  {
    "Name": "TheWestinValencia",
    "Category": "Luxury",
    "Location": "Valencia, Spain",
    "StarRating": 5
  },
  {
    "Name": "Badrutt",
    "Category": "Luxury",
    "Location": "St. Moritz, Switzerland",
    "StarRating": 5
  },
  {
    "Name": "TheDolderGrandZurich",
    "Category": "Luxury",
    "Location": "Zurich, Switzerland",
    "StarRating": 5
  },
  {
    "Name": "HotelBeauRivageGeneva",
    "Category": "Deluxe",
    "Location": "Geneva, Switzerland",
    "StarRating": 4
  },
  {
    "Name": "SonevaFushiMaldives",
    "Category": "Luxury",
    "Location": "Maldives",
    "StarRating": 5
  },
  {
    "Name": "AnantaraVeliMaldives",
    "Category": "Luxury",
    "Location": "Maldives",
    "StarRating": 5
  },
  {
    "Name": "COMOMaalifushiMaldives",
    "Category": "Resort",
    "Location": "Maldives",
    "StarRating": 5
  },
  {
    "Name": "MarinaBaySandsSingapore",
    "Category": "Luxury",
    "Location": "Singapore",
    "StarRating": 5
  },
  {
    "Name": "RafflesHotelSingapore",
    "Category": "Luxury",
    "Location": "Singapore",
    "StarRating": 5
  },
  {
    "Name": "FullertonHotelSingapore",
    "Category": "Deluxe",
    "Location": "Singapore",
    "StarRating": 4
  }
]
